test.py
entrez_utils/__init__.py
entrez_utils/entrez.py
entrez_utils/entrez_bio_object.py
entrez_utils/ncbi.py
entrez_utils/sra_files.py
entrez_utils/sra_library.py
entrez_utils/sra_utils.py
entrez_utils/url_path.py
entrez_utils/xml_data.py
entrez_utils-0.0.3.dist-info/LICENSE
entrez_utils-0.0.3.dist-info/METADATA
entrez_utils-0.0.3.dist-info/WHEEL
entrez_utils-0.0.3.dist-info/top_level.txt
entrez_utils-0.0.3.dist-info/RECORD
