Metadata-Version: 2.1
Name: entrez_utils
Version: 0.0.3
Summary: A library for accessing NCBI Entrez databases.
Author-email: Andrew Tapia <andrew.tapia@uky.edu>
Project-URL: Homepage, https://github.com/actapia/entrez_utils
Project-URL: Bug Tracker, https://github.com/actapia/entrez_utils
Classifier: Programming Language :: Python :: 3
Classifier: License :: OSI Approved :: MIT License
Classifier: Operating System :: OS Independent
Requires-Python: >=3.8
License-File: LICENSE
Requires-Dist: lxml
Requires-Dist: requests
